{
  "project_info": {
    "project_number": "1083406847577",
    "project_id": "connectmarinan",
    "storage_bucket": "connectmarinan.firebasestorage.app"
  },
  "client": [
    {
      "client_info": {
        "mobilesdk_app_id": "1:1083406847577:android:4a3cb65b53924472a66b48",
        "android_client_info": {
          "package_name": "com.example.connectmarian"
        }
      },
      "oauth_client": [],
      "api_key": [
        {
          "current_key": "AIzaSyCqz0PMIHKt-bxQ_LpipMsAESBx5rRTbIA"
        }
      ],
      "services": {
        "appinvite_service": {
          "other_platform_oauth_client": []
        }
      }
    }
  ],
  "configuration_version": "1"
}